muzak2yt/__init__.py
muzak2yt/__main__.py
muzak2yt-1.0.2.dist-info/LICENSE
muzak2yt-1.0.2.dist-info/METADATA
muzak2yt-1.0.2.dist-info/WHEEL
muzak2yt-1.0.2.dist-info/top_level.txt
muzak2yt-1.0.2.dist-info/RECORD
