Metadata-Version: 2.1
Name: muzak2yt
Version: 1.0.2
Summary: Upload your favorite music albums directly to YouTube !
Home-page: https://github.com/Sakimotor/muzak2yt
Author: Sakimotor
License: UNKNOWN
Project-URL: Bug Tracker, https://github.com/Sakimotor/muzak2yt/issues
Platform: UNKNOWN
Classifier: Programming Language :: Python :: 3
Classifier: License :: OSI Approved :: GNU General Public License v3 or later (GPLv3+)
Classifier: Operating System :: OS Independent
Requires-Python: >=3.6
